gnoll-4.5.5.data/purelib/gnoll/__init__.py
gnoll-4.5.5.data/purelib/gnoll/__main__.py
gnoll-4.5.5.data/purelib/gnoll/c_build/dice
gnoll-4.5.5.data/purelib/gnoll/c_build/dice.so
gnoll-4.5.5.data/purelib/gnoll/c_build/lex.yy.c
gnoll-4.5.5.data/purelib/gnoll/c_build/lex.yy.o
gnoll-4.5.5.data/purelib/gnoll/c_build/libdice.so
gnoll-4.5.5.data/purelib/gnoll/c_build/y.tab.c
gnoll-4.5.5.data/purelib/gnoll/c_build/y.tab.h
gnoll-4.5.5.data/purelib/gnoll/c_build/y.tab.o
gnoll-4.5.5.data/purelib/gnoll/c_build/operations/conditionals.o
gnoll-4.5.5.data/purelib/gnoll/c_build/operations/macros.o
gnoll-4.5.5.data/purelib/gnoll/c_build/rolls/dice_core.o
gnoll-4.5.5.data/purelib/gnoll/c_build/rolls/dice_frontend.o
gnoll-4.5.5.data/purelib/gnoll/c_build/rolls/randomness.o
gnoll-4.5.5.data/purelib/gnoll/c_build/util/array_functions.o
gnoll-4.5.5.data/purelib/gnoll/c_build/util/mocking.o
gnoll-4.5.5.data/purelib/gnoll/c_build/util/safe_functions.o
gnoll-4.5.5.data/purelib/gnoll/c_build/util/string_functions.o
gnoll-4.5.5.data/purelib/gnoll/c_build/util/vector_functions.o
gnoll-4.5.5.data/purelib/gnoll/c_includes/src/grammar/dice.lex
gnoll-4.5.5.data/purelib/gnoll/c_includes/src/grammar/dice.yacc
gnoll-4.5.5.data/purelib/gnoll/c_includes/src/grammar/shared_header.h
gnoll-4.5.5.data/purelib/gnoll/c_includes/src/grammar/constructs/dice_enums.h
gnoll-4.5.5.data/purelib/gnoll/c_includes/src/grammar/constructs/roll_parameters.h
gnoll-4.5.5.data/purelib/gnoll/c_includes/src/grammar/constructs/vec.h
gnoll-4.5.5.data/purelib/gnoll/c_includes/src/grammar/external/tinydir.h
gnoll-4.5.5.data/purelib/gnoll/c_includes/src/grammar/external/uthash.h
gnoll-4.5.5.data/purelib/gnoll/c_includes/src/grammar/external/pcg-c/.git
gnoll-4.5.5.data/purelib/gnoll/c_includes/src/grammar/external/pcg-c/.gitignore
gnoll-4.5.5.data/purelib/gnoll/c_includes/src/grammar/external/pcg-c/CONTRIBUTING.md
gnoll-4.5.5.data/purelib/gnoll/c_includes/src/grammar/external/pcg-c/LICENSE-APACHE.txt
gnoll-4.5.5.dist-info/METADATA
gnoll-4.5.5.dist-info/WHEEL
gnoll-4.5.5.dist-info/top_level.txt
gnoll-4.5.5.dist-info/RECORD
