Metadata-Version: 2.4
Name: gnoll
Version: 4.5.5
Summary: An efficient dice notation parser with extended notation
Home-page: https://github.com/ianfhunter/gnoll
Author: Ian Frederick Vigogne Goodbody Hunter
Author-email: ianfhunter@gmail.com
Project-URL: Bug Tracker, https://github.com/ianfhunter/gnoll/issues
Classifier: Development Status :: 5 - Production/Stable
Classifier: Programming Language :: Unix Shell
Classifier: Programming Language :: C
Classifier: Programming Language :: Python :: 3
Classifier: License :: OSI Approved :: MIT License
Classifier: Operating System :: Unix
Classifier: Intended Audience :: Developers
Classifier: Intended Audience :: Science/Research
Classifier: Intended Audience :: Other Audience
Classifier: License :: OSI Approved :: GNU General Public License v3 (GPLv3)
Classifier: Topic :: Games/Entertainment :: Board Games
Classifier: Topic :: Games/Entertainment :: Role-Playing
Classifier: Topic :: Scientific/Engineering :: Mathematics
Classifier: Topic :: Software Development :: Interpreters
Classifier: Topic :: Software Development :: Libraries :: Python Modules
Classifier: Topic :: Text Processing
Requires-Python: >=3.6
